videomass/__init__.py
videomass/gui_app.py
videomass/data/hicolor/256x256/apps/videomass.png
videomass/data/hicolor/48x48/apps/videomass.png
videomass/data/hicolor/48x48/apps/videomass.xpm
videomass/data/hicolor/scalable/apps/videomass.svg
videomass/data/icons/videomass.png
videomass/data/icons/Sign_Icons/48x48/icon_concat.png
videomass/data/icons/Sign_Icons/48x48/icon_concat.svg
videomass/data/icons/Sign_Icons/48x48/icon_prst_mng.png
videomass/data/icons/Sign_Icons/48x48/icon_prst_mng.svg
videomass/data/icons/Sign_Icons/48x48/icon_slideshow.png
videomass/data/icons/Sign_Icons/48x48/icon_slideshow.svg
videomass/data/icons/Sign_Icons/48x48/icon_videoconversions.png
videomass/data/icons/Sign_Icons/48x48/icon_videoconversions.svg
videomass/data/icons/Sign_Icons/48x48/icon_videopictures.png
videomass/data/icons/Sign_Icons/48x48/icon_videopictures.svg
videomass/data/icons/Sign_Icons/48x48/youtube.png
videomass/data/icons/Sign_Icons/48x48/youtube.svg
videomass/data/icons/Sign_Icons/48x48_dark/icon_concat.png
videomass/data/icons/Sign_Icons/48x48_dark/icon_concat.svg
videomass/data/icons/Sign_Icons/48x48_dark/icon_prst_mng.png
videomass/data/icons/Sign_Icons/48x48_dark/icon_prst_mng.svg
videomass/data/icons/Sign_Icons/48x48_dark/icon_slideshow.png
videomass/data/icons/Sign_Icons/48x48_dark/icon_slideshow.svg
videomass/data/icons/Sign_Icons/48x48_dark/icon_videoconversions.png
videomass/data/icons/Sign_Icons/48x48_dark/icon_videoconversions.svg
videomass/data/icons/Sign_Icons/48x48_dark/icon_videopictures.png
videomass/data/icons/Sign_Icons/48x48_dark/icon_videopictures.svg
videomass/data/icons/Sign_Icons/48x48_dark/youtube.png
videomass/data/icons/Sign_Icons/48x48_dark/youtube.svg
videomass/data/icons/Sign_Icons/48x48_light/icon_concat.png
videomass/data/icons/Sign_Icons/48x48_light/icon_concat.svg
videomass/data/icons/Sign_Icons/48x48_light/icon_prst_mng.png
videomass/data/icons/Sign_Icons/48x48_light/icon_prst_mng.svg
videomass-6.1.20.dist-info/METADATA
videomass-6.1.20.dist-info/WHEEL
videomass-6.1.20.dist-info/entry_points.txt
videomass-6.1.20.dist-info/licenses/AUTHORS
videomass-6.1.20.dist-info/licenses/LICENSE
videomass-6.1.20.dist-info/RECORD
