Metadata-Version: 2.4
Name: videomass
Version: 6.1.20
Summary: Videomass is a cross-platform GUI for FFmpeg
Project-URL: Homepage, https://jeanslack.github.io/Videomass/
Project-URL: Documentation, https://jeanslack.github.io/Videomass/Docs.html
Project-URL: Wiki, https://github.com/jeanslack/Videomass/wiki
Project-URL: Repository, https://github.com/jeanslack/Videomass
Project-URL: Issues, https://github.com/jeanslack/Videomass/issues
Author-email: Gianluca Pernigotto <jeanlucperni@gmail.com>
Maintainer-email: Gianluca Pernigotto <jeanlucperni@gmail.com>
License: GNU General Public License v3 (GPLv3)
License-File: AUTHORS
License-File: LICENSE
Keywords: converter,converters,ffmpeg,videomass,wxpython
Classifier: Development Status :: 5 - Production/Stable
Classifier: Environment :: X11 Applications :: GTK
Classifier: Intended Audience :: End Users/Desktop
Classifier: License :: OSI Approved :: GNU General Public License v3 (GPLv3)
Classifier: Natural Language :: Arabic
Classifier: Natural Language :: Chinese (Simplified)
Classifier: Natural Language :: Czech
Classifier: Natural Language :: Dutch
Classifier: Natural Language :: English
Classifier: Natural Language :: French
Classifier: Natural Language :: German
Classifier: Natural Language :: Hungarian
Classifier: Natural Language :: Italian
Classifier: Natural Language :: Portuguese (Brazilian)
Classifier: Natural Language :: Russian
Classifier: Natural Language :: Spanish
Classifier: Operating System :: MacOS
Classifier: Operating System :: Microsoft :: Windows
Classifier: Operating System :: POSIX :: Linux
Classifier: Programming Language :: Python :: 3 :: Only
Classifier: Programming Language :: Python :: 3.9
Classifier: Programming Language :: Python :: 3.10
Classifier: Programming Language :: Python :: 3.11
Classifier: Programming Language :: Python :: 3.12
Classifier: Programming Language :: Python :: 3.13
Classifier: Topic :: Multimedia :: Sound/Audio :: Conversion
Classifier: Topic :: Multimedia :: Video
Classifier: Topic :: Multimedia :: Video :: Conversion
Requires-Python: >=3.9
Requires-Dist: pypubsub>=4.0.3
Requires-Dist: requests
Requires-Dist: wxpython>=4.0.7; platform_system == 'Windows' or platform_system == 'Darwin'
Provides-Extra: build
Requires-Dist: babel; extra == 'build'
Requires-Dist: build; extra == 'build'
Requires-Dist: hatchling; extra == 'build'
Requires-Dist: pip; extra == 'build'
Requires-Dist: setuptools; extra == 'build'
Requires-Dist: six; extra == 'build'
Requires-Dist: wheel; extra == 'build'
Provides-Extra: cli
Provides-Extra: pyinstaller
Requires-Dist: pyinstaller; extra == 'pyinstaller'
